velocity_estimation/__init__.py
velocity_estimation/conditional_averaging.py
velocity_estimation/correlation.py
velocity_estimation/time_delay_estimation.py
velocity_estimation/two_dim_velocity_estimates.py
velocity_estimation/utils.py
velocity_estimation-1.0.0.dist-info/LICENSE
velocity_estimation-1.0.0.dist-info/METADATA
velocity_estimation-1.0.0.dist-info/WHEEL
velocity_estimation-1.0.0.dist-info/top_level.txt
velocity_estimation-1.0.0.dist-info/RECORD
