Metadata-Version: 2.1
Name: velocity-estimation
Version: 1.0.0
Summary: Python scripts for velocity estimation in turbulent flows
Home-page: https://github.com/uit-cosmo/velocity-estimation
Download-URL: https://github.com/uit-cosmo/velocity-estimation/archive/refs/tags/1.1.tar.gz
Author: Juan Manuel Losada
Author-email: juan.m.losada@uit.no
License: MiT
Classifier: Intended Audience :: Education
Classifier: Intended Audience :: Science/Research
Classifier: License :: OSI Approved :: MIT License
Classifier: Programming Language :: Python :: 3 :: Only
Classifier: Topic :: Scientific/Engineering :: Visualization
Requires-Python: >=3.0
License-File: LICENSE
Requires-Dist: blobmodel >=1.0.0
Requires-Dist: numpy >=1.23.3
Requires-Dist: scipy >=1.11.3
